isweep/__init__.py
isweep/coalescent.py
isweep/favoredalleles.py
isweep/inference.py
isweep/outgroups.py
isweep/slow.py
isweep/utilities.py
isweep-1.1.3.dist-info/METADATA
isweep-1.1.3.dist-info/WHEEL
isweep-1.1.3.dist-info/licenses/LICENSE
isweep-1.1.3.dist-info/RECORD
