Metadata-Version: 2.4
Name: isweep
Version: 1.1.3
Summary: Methods for selective sweep inference
Project-URL: Homepage, https://github.com/sdtemple/isweep
Project-URL: Bug Tracker, https://github.com/sdtemple/isweep/issues
Author-email: "Seth D. Temple" <sethtem@umich.edu>
License-File: LICENSE
Classifier: Development Status :: 4 - Beta
Classifier: License :: CC0 1.0 Universal (CC0 1.0) Public Domain Dedication
Classifier: Operating System :: OS Independent
Classifier: Programming Language :: Python :: 3
Requires-Python: >=3.7
Requires-Dist: networkx
Requires-Dist: numpy>=1.21
Requires-Dist: pandas
Requires-Dist: scipy>=1.7
